dbzero-0.1.3.dist-info/METADATA
dbzero-0.1.3.dist-info/WHEEL
dbzero-0.1.3.dist-info/LICENSE
dbzero/libs/libpyzero.a
dbzero/dbzero.cp310-win_amd64.pyd
dbzero/dbzero.cp310-win_amd64.lib
dbzero/__init__.py
dbzero/atomic.py
dbzero/compare.py
dbzero/dbzero.py
dbzero/dbzero.pyi
dbzero/decorators.py
dbzero/enum.py
dbzero/fast_query.py
dbzero/initialization.py
dbzero/interfaces.py
dbzero/locked.py
dbzero/memo.py
dbzero/reflection_api.py
dbzero/select.py
dbzero/storage_api.py
dbzero/utilities.py
dbzero/LICENSE
dbzero/NOTICE
dbzero/GOOGLETEST_LICENSE
dbzero/BOOST_LICENSE_1_0
dbzero-0.1.3.dist-info/RECORD
