Metadata-Version: 2.1
Name: dbzero
Version: 0.1.3
Summary: A state management system for Python 3.x that unifies your applications business logic, data persistence, and caching into a single, efficient layer.
Author-Email: "DBZero Software sp. z o.o" <info@dbzero.io>
License:                   GNU LESSER GENERAL PUBLIC LICENSE
Classifier: Programming Language :: Python :: 3
Classifier: Programming Language :: Python :: 3 :: Only
Project-URL: homepage, https://dbzero.io/
Project-URL: documentation, https://docs.dbzero.io/
Project-URL: repository, https://github.com/dbzero-software/dbzero
Requires-Python: >=3.9
Requires-Dist: fasteners==0.19
